pandemic/__init__.py
pandemic/data_unloader.py
pandemic/functions.py
pandemic/turn_handler.py
pandemic/world_map_drawer.py
pandemic/pictures/background_image.png
pandemic/pictures/infection_card_back.png
pandemic/pictures/medic.png
pandemic/pictures/operations_expert.png
pandemic/pictures/player_card_back.png
pandemic/pictures/quarantine_specialist.png
pandemic/pictures/scientist.png
pandemic/pictures/world_map.png
pandemic/variables/cities_data.txt
pandemic/variables/infection_cards.txt
pandemic/variables/other_cards.txt
pandemic_scipy-6.0.0.dist-info/METADATA
pandemic_scipy-6.0.0.dist-info/WHEEL
pandemic_scipy-6.0.0.dist-info/top_level.txt
pandemic_scipy-6.0.0.dist-info/RECORD
