Metadata-Version: 2.4
Name: pandemic-scipy
Version: 6.0.0
Summary: A Python simulation package for pandemic game logic
Author-email: Bartha Lilla <barthalilla1@gmail.com>, Kerényi Kornél <kerenyikornel@gmail.com>, Tolvaj Tamás <tolvaktomi@gmail.com>
License: MIT
Requires-Python: >=3.9
Requires-Dist: sphinx
Requires-Dist: sphinx-rtd-theme
Requires-Dist: Pillow
